nonebot_plugin_broker/__init__.py
nonebot_plugin_broker/command.py
nonebot_plugin_broker/config.py
nonebot_plugin_broker/interface.py
nonebot_plugin_broker/internal.py
nonebot_plugin_broker/topic.py
nonebot_plugin_broker-0.4.1.dist-info/LICENSE
nonebot_plugin_broker-0.4.1.dist-info/WHEEL
nonebot_plugin_broker-0.4.1.dist-info/METADATA
nonebot_plugin_broker-0.4.1.dist-info/RECORD
