Metadata-Version: 2.1
Name: nonebot-plugin-broker
Version: 0.4.1
Summary: a plugin for nonebot
License: MIT
Author: mwbimh
Author-email: mwbimh@gmail.com
Requires-Python: >=3.7.13,<4.0.0
Classifier: License :: OSI Approved :: MIT License
Classifier: Programming Language :: Python :: 3
Classifier: Programming Language :: Python :: 3.10
Classifier: Programming Language :: Python :: 3.8
Classifier: Programming Language :: Python :: 3.9
Requires-Dist: asyncio (>=3.4.3,<4.0.0)
Requires-Dist: nonebot-adapter-onebot (>=2.0.0-beta.1,<3.0.0)
Requires-Dist: nonebot-plugin-apscheduler (>=0.1.2,<0.2.0)
Requires-Dist: nonebot2 (>=2.0.0-beta.2,<3.0.0)
Requires-Dist: ruamel.yaml (>=0.17.21,<0.18.0)
